Metadata-Version: 2.1
Name: colcon-lint
Version: 0.2.0
Summary: Colcon extension for linting ROS package dependencies
Home-page: UNKNOWN
Author: Tatsuro Sakaguchi
Author-email: tacchan.mello.ioiq@gmail.com
Maintainer: Tatsuro Sakaguchi
Maintainer-email: tacchan.mello.ioiq@gmail.com
License: Apache License, Version 2.0
Project-URL: GitHub, https://github.com/Tacha-S/colcon-lint/
Keywords: colcon
Platform: UNKNOWN
Requires-Python: >=3.10
License-File: LICENSE
